lapis/__init__.py
lapis/command.py
lapis/config.py
lapis/editor.py
lapis/formats.py
lapis/models.py
lapis/printer.py
lapis/slug.py
lapis/store.py
lapis/version.py
lapis/writer.py
lapis/examples/lapis.yml
lapis/templates/article-markdown.jinja
lapis/templates/article-restructuredtext.jinja
lapis/templates/page-markdown.jinja
lapis/templates/page-restructuredtext.jinja
lapis-0.2.1b.dist-info/DESCRIPTION.rst
lapis-0.2.1b.dist-info/entry_points.txt
lapis-0.2.1b.dist-info/METADATA
lapis-0.2.1b.dist-info/metadata.json
lapis-0.2.1b.dist-info/RECORD
lapis-0.2.1b.dist-info/top_level.txt
lapis-0.2.1b.dist-info/WHEEL
