Metadata-Version: 2.0
Name: lapis
Version: 0.2.1b
Summary: Perform pelican tasks easily
Home-page: http://github.com/dandesousa/lapis
Author: Daniel DeSousa
Author-email: dan+lapis@desousa.cc
License: CC0 1.0 Universal
Platform: any
Classifier: Development Status :: 4 - Beta
Classifier: Programming Language :: Python :: 3.3
Classifier: Programming Language :: Python :: 3.4
Requires-Dist: pelican
Requires-Dist: SQLAlchemy
Requires-Dist: Markdown
Requires-Dist: PyYaml
Requires-Dist: termcolor
